{"cli_decrypt.md":"3lDxLriv","cli_download.md":"BJA5aRiA","cli_officialaccount.md":"C_fH9gFt","cli_proxy.md":"D6gNAcau","cli_server.md":"Beou7e6i","cli_sph.md":"FABAK0SA","cli_uninstall.md":"D1KVplzH","cli_update.md":"Cnz_jcOH","cli_version.md":"pZpBHis_","config_api.md":"DDCNIGV9","config_cert.md":"BZ3SNCy8","config_channels.md":"Atf-1oaI","config_cloudflare.md":"_b0MCC0F","config_debug.md":"CQwsXPR3","config_download.md":"5h8IeoRj","config_officialacount.md":"Ct8BDwCK","config_proxy.md":"DvPHZu7S","config_script.md":"Bhz8Rk5H","faq_button_inject_failed.md":"BD-Vqw2E","faq_decrypt_fail.md":"C27Ut88C","faq_download_stuck.md":"t_ZJxNyR","faq_network_failed.md":"BTFP-O1m","faq_powershell.md":"DLx68d-J","faq_task_create_crash_fix.md":"BE2b0-br","faq_windows_service_timeout.md":"-cx8oXj5","feature_api.md":"CF1cSXGZ","feature_batch.md":"CJrK43na","feature_custom-menu.md":"CmhqZ9rw","feature_event.md":"Bg1sJSE0","feature_filename.md":"C6djDiJt","feature_live.md":"fUyAaHR9","feature_long-video.md":"CByPQHJv","feature_mp-rss.md":"UCvM3RSQ","feature_mp3.md":"0Mc4DJgz","feature_officialaccount.md":"CdsdHh1U","feature_playground.md":"BhGMfK4x","guide_certificate.md":"WGFJRqmr","guide_macos.md":"CZ7Ny4Eq","guide_start.md":"Bd0h8chF","guide_step.md":"DxUjbmjW","index.md":"BzU28pfs","releases.md":"CBJnk3fc","releases_241011.md":"De2-UQX_","releases_241016.md":"y5591Sxd","releases_241022.md":"C03zjvSh","releases_241030.md":"DPPfhRNx","releases_241031.md":"CpIkEeUh","releases_241101.md":"BhX2nWpW","releases_241102.md":"iLevyT6v","releases_241104.md":"DxeDdudx","releases_241106.md":"BnfFw8P4","releases_241216.md":"rHnvjg8o","releases_250215.md":"xRx5Ha6m","releases_250424.md":"CbJh5aXd","releases_250425.md":"DVtkag2k","releases_250514.md":"D-YRWkr8","releases_250621.md":"D2afgquR","releases_250808.md":"D9L88b6d","releases_250913.md":"D61wtL_M","releases_251027.md":"C4tj3wr2","releases_251122.md":"Cn-YCkmN","releases_251130.md":"E0eZ3U4E","releases_251201.md":"TNfJ6BU5","releases_251202.md":"Ds1MvaRW","releases_251203.md":"BaiRtjBu","releases_251213.md":"775uk3yC","releases_251226.md":"CCjfsZ9N","releases_251231.md":"CdvYBNij","releases_260110.md":"wZPEqMJS","releases_260118.md":"DMrc9IgG","releases_260201.md":"DPQ5lCc9","releases_260208.md":"CCDLTyCN","releases_260302.md":"BS8AcRWj","releases_260310.md":"gfH9Os_T","releases_260311.md":"tIh4urSj","releases_260317.md":"B1nmh0Rt","releases_260323.md":"DxMflZwi","releases_260324.md":"C87Anlqj","releases_260502.md":"S3l7SO_M","releases_260507.md":"O_ic8LVw","releases_260520.md":"mKaQ78Z_","releases_260524.md":"ClaTuPJx","releases_260531.md":"Cd2Tprvd"}
